pyjsonedit/__init__.py
pyjsonedit/cli.py
pyjsonedit/editor.py
pyjsonedit/main.py
pyjsonedit/matcher.py
pyjsonedit/node_modify_action.py
pyjsonedit/parser.py
pyjsonedit/token_list.py
pyjsonedit/tokenizer.py
pyjsonedit-1.0.4.dist-info/entry_points.txt
pyjsonedit-1.0.4.dist-info/LICENSE
pyjsonedit-1.0.4.dist-info/WHEEL
pyjsonedit-1.0.4.dist-info/METADATA
pyjsonedit-1.0.4.dist-info/RECORD
